{
  "status": 200,
  "data": {
    "maxResults": 50,
    "startAt": 0,
    "total": 5,
    "isLast": true,
    "values": [
      {
        "self": "https://task.wemakedev.ru/rest/api/2/issuetype/10000",
        "id": "10000",
        "description": "Создано Jira Software — не изменять и не удалять. Тип задачи для большой пользовательской истории, требующей декомпозиции.",
        "iconUrl": "https://task.wemakedev.ru/images/icons/issuetypes/epic.svg",
        "name": "Epic",
        "subtask": false
      },
      {
        "self": "https://task.wemakedev.ru/rest/api/2/issuetype/10001",
        "id": "10001",
        "description": "Создано Jira Software — не изменять и не удалять. Тип задачи для пользовательской истории.",
        "iconUrl": "https://task.wemakedev.ru/images/icons/issuetypes/story.svg",
        "name": "История",
        "subtask": false
      },
      {
        "self": "https://task.wemakedev.ru/rest/api/2/issuetype/10100",
        "id": "10100",
        "description": "Задание для выполнения.",
        "iconUrl": "https://task.wemakedev.ru/secure/viewavatar?size=xsmall&avatarId=10318&avatarType=issuetype",
        "name": "Задача",
        "subtask": false
      },
      {
        "self": "https://task.wemakedev.ru/rest/api/2/issuetype/10101",
        "id": "10101",
        "description": "Подзадача запроса.",
        "iconUrl": "https://task.wemakedev.ru/secure/viewavatar?size=xsmall&avatarId=10316&avatarType=issuetype",
        "name": "Подзадача",
        "subtask": true
      },
      {
        "self": "https://task.wemakedev.ru/rest/api/2/issuetype/10102",
        "id": "10102",
        "description": "",
        "iconUrl": "https://task.wemakedev.ru/secure/viewavatar?size=xsmall&avatarId=10303&avatarType=issuetype",
        "name": "Ошибка",
        "subtask": false
      }
    ]
  }
}